{"errors":[],"warnings":[],"namedChunkGroups":{"polyfill":{"chunks":[2,0,9],"assets":["webpack-runtime-9f94e6fe903d42f70d1e.js","webpack-runtime-9f94e6fe903d42f70d1e.js.map","commons-70eca93cf4177c70f37a.js","commons-70eca93cf4177c70f37a.js.map","polyfill-da901081db5f1889332d.js","polyfill-da901081db5f1889332d.js.map"],"children":{},"childAssets":{}},"app":{"chunks":[2,1,8,3],"assets":["webpack-runtime-9f94e6fe903d42f70d1e.js","webpack-runtime-9f94e6fe903d42f70d1e.js.map","styles.128ca5b3dc3aafe36817.css","styles-c2fe8482057191dca484.js","styles-c2fe8482057191dca484.js.map","framework-63ec46a3540d83159f28.js","framework-63ec46a3540d83159f28.js.map","app-006ee2037494af9a2655.js","app-006ee2037494af9a2655.js.map"],"children":{},"childAssets":{}},"component---src-pages-404-js":{"chunks":[1,0,4],"assets":["styles.128ca5b3dc3aafe36817.css","styles-c2fe8482057191dca484.js","styles-c2fe8482057191dca484.js.map","commons-70eca93cf4177c70f37a.js","commons-70eca93cf4177c70f37a.js.map","component---src-pages-404-js-795ccb63df2709875bfb.js","component---src-pages-404-js-795ccb63df2709875bfb.js.map"],"children":{},"childAssets":{}},"component---src-pages-blog-js":{"chunks":[1,0,5],"assets":["styles.128ca5b3dc3aafe36817.css","styles-c2fe8482057191dca484.js","styles-c2fe8482057191dca484.js.map","commons-70eca93cf4177c70f37a.js","commons-70eca93cf4177c70f37a.js.map","component---src-pages-blog-js-548356d3a304a8412a24.js","component---src-pages-blog-js-548356d3a304a8412a24.js.map"],"children":{},"childAssets":{}},"component---src-pages-index-js":{"chunks":[1,0,6],"assets":["styles.128ca5b3dc3aafe36817.css","styles-c2fe8482057191dca484.js","styles-c2fe8482057191dca484.js.map","commons-70eca93cf4177c70f37a.js","commons-70eca93cf4177c70f37a.js.map","component---src-pages-index-js-ba776da399e685ef879c.js","component---src-pages-index-js-ba776da399e685ef879c.js.map"],"children":{},"childAssets":{}},"component---src-templates-blog-post-js":{"chunks":[1,0,7],"assets":["styles.128ca5b3dc3aafe36817.css","styles-c2fe8482057191dca484.js","styles-c2fe8482057191dca484.js.map","commons-70eca93cf4177c70f37a.js","commons-70eca93cf4177c70f37a.js.map","component---src-templates-blog-post-js-211fd301275fd857341d.js","component---src-templates-blog-post-js-211fd301275fd857341d.js.map"],"children":{},"childAssets":{}}},"assetsByChunkName":{"polyfill":["webpack-runtime-9f94e6fe903d42f70d1e.js","commons-70eca93cf4177c70f37a.js","polyfill-da901081db5f1889332d.js"],"app":["webpack-runtime-9f94e6fe903d42f70d1e.js","styles.128ca5b3dc3aafe36817.css","styles-c2fe8482057191dca484.js","framework-63ec46a3540d83159f28.js","app-006ee2037494af9a2655.js"],"component---src-pages-404-js":["styles.128ca5b3dc3aafe36817.css","styles-c2fe8482057191dca484.js","commons-70eca93cf4177c70f37a.js","component---src-pages-404-js-795ccb63df2709875bfb.js"],"component---src-pages-blog-js":["styles.128ca5b3dc3aafe36817.css","styles-c2fe8482057191dca484.js","commons-70eca93cf4177c70f37a.js","component---src-pages-blog-js-548356d3a304a8412a24.js"],"component---src-pages-index-js":["styles.128ca5b3dc3aafe36817.css","styles-c2fe8482057191dca484.js","commons-70eca93cf4177c70f37a.js","component---src-pages-index-js-ba776da399e685ef879c.js"],"component---src-templates-blog-post-js":["styles.128ca5b3dc3aafe36817.css","styles-c2fe8482057191dca484.js","commons-70eca93cf4177c70f37a.js","component---src-templates-blog-post-js-211fd301275fd857341d.js"]}}